starlette_testclient/__init__.py
starlette_testclient/_testclient.py
starlette_testclient/py.typed
starlette_testclient-0.4.0.dist-info/METADATA
starlette_testclient-0.4.0.dist-info/WHEEL
starlette_testclient-0.4.0.dist-info/licenses/LICENSE
starlette_testclient-0.4.0.dist-info/RECORD
