Metadata-Version: 2.3
Name: starlette-testclient
Version: 0.4.0
Summary: A backport of Starlette TestClient using requests! ⏪️
Project-URL: Homepage, https://github.com/Kludex/starlette-testclient
Project-URL: Source, https://github.com/Kludex/starlette-testclient
Project-URL: Twitter, https://twitter.com/marcelotryle
Project-URL: Funding, https://github.com/sponsors/Kludex
Author-email: Marcelo Trylesinski <marcelotryle@email.com>
License-Expression: BSD-3-Clause
License-File: LICENSE
Classifier: Development Status :: 3 - Alpha
Classifier: Intended Audience :: Developers
Classifier: License :: OSI Approved :: BSD License
Classifier: Natural Language :: English
Classifier: Operating System :: OS Independent
Classifier: Programming Language :: Python :: 3
Classifier: Programming Language :: Python :: 3 :: Only
Classifier: Programming Language :: Python :: 3.7
Classifier: Programming Language :: Python :: 3.8
Classifier: Programming Language :: Python :: 3.9
Classifier: Programming Language :: Python :: 3.10
Classifier: Programming Language :: Python :: 3.11
Classifier: Programming Language :: Python :: 3.12
Requires-Python: >=3.7
Requires-Dist: requests
Requires-Dist: starlette>=0.20.1
